{
  "frame_id": 13448,
  "weather": "fog_heavy",
  "num_points": 8300,
  "num_radar": 102,
  "objects": [
    {
      "class": "vehicle",
      "actor_id": 377,
      "bbox_2d": [
        363,
        323,
        443,
        404
      ],
      "bbox_3d": [
        41.851,
        220.027,
        0.259,
        1.994,
        0.925,
        0.809,
        89.96
      ],
      "distance": 12.71,
      "occluded": false
    },
    {
      "class": "vehicle",
      "actor_id": 370,
      "bbox_2d": [
        340,
        305,
        370,
        330
      ],
      "bbox_3d": [
        45.854,
        242.605,
        0.219,
        2.302,
        0.966,
        0.927,
        -90.01
      ],
      "distance": 35.51,
      "occluded": false
    },
    {
      "class": "vehicle",
      "actor_id": 363,
      "bbox_2d": [
        398,
        304,
        409,
        314
      ],
      "bbox_3d": [
        41.858,
        275.212,
        0.212,
        1.853,
        0.894,
        0.775,
        90.08
      ],
      "distance": 67.89,
      "occluded": false
    },
    {
      "class": "vehicle",
      "actor_id": 354,
      "bbox_2d": [
        0,
        240,
        231,
        599
      ],
      "bbox_3d": [
        45.816,
        212.714,
        0.198,
        2.958,
        0.994,
        1.28,
        -89.5
      ],
      "distance": 6.71,
      "occluded": false
    },
    {
      "class": "vehicle",
      "actor_id": 351,
      "bbox_2d": [
        366,
        305,
        384,
        317
      ],
      "bbox_3d": [
        45.857,
        265.87,
        0.254,
        2.451,
        1.064,
        0.755,
        -90.01
      ],
      "distance": 58.69,
      "occluded": false
    },
    {
      "class": "vehicle",
      "actor_id": 341,
      "bbox_2d": [
        358,
        307,
        379,
        321
      ],
      "bbox_3d": [
        45.855,
        256.109,
        0.213,
        2.679,
        1.017,
        0.705,
        -90.01
      ],
      "distance": 48.95,
      "occluded": false
    },
    {
      "class": "vehicle",
      "actor_id": 340,
      "bbox_2d": [
        396,
        304,
        410,
        316
      ],
      "bbox_3d": [
        41.857,
        267.905,
        0.22,
        2.619,
        0.965,
        0.819,
        89.99
      ],
      "distance": 60.58,
      "occluded": false
    }
  ]
}