{
  "frame_id": 3442,
  "weather": "clear",
  "num_points": 18267,
  "num_radar": 129,
  "objects": [
    {
      "class": "vehicle",
      "actor_id": 245,
      "bbox_2d": [
        516,
        322,
        668,
        361
      ],
      "bbox_3d": [
        135.629,
        229.097,
        0.213,
        2.679,
        1.017,
        0.705,
        -85.7
      ],
      "distance": 19.91,
      "occluded": false
    },
    {
      "class": "vehicle",
      "actor_id": 243,
      "bbox_2d": [
        780,
        296,
        799,
        350
      ],
      "bbox_3d": [
        132.107,
        213.723,
        0.2,
        2.958,
        0.994,
        1.28,
        89.72
      ],
      "distance": 31.86,
      "occluded": false
    },
    {
      "class": "vehicle",
      "actor_id": 238,
      "bbox_2d": [
        689,
        305,
        720,
        316
      ],
      "bbox_3d": [
        92.851,
        191.595,
        0.21,
        1.853,
        0.894,
        0.775,
        0.05
      ],
      "distance": 76.07,
      "occluded": false
    },
    {
      "class": "vehicle",
      "actor_id": 235,
      "bbox_2d": [
        695,
        316,
        799,
        349
      ],
      "bbox_3d": [
        132.132,
        219.445,
        0.212,
        1.853,
        0.894,
        0.775,
        90.17
      ],
      "distance": 27.95,
      "occluded": false
    },
    {
      "class": "vehicle",
      "actor_id": 234,
      "bbox_2d": [
        341,
        326,
        463,
        444
      ],
      "bbox_3d": [
        143.31,
        236.856,
        0.211,
        2.428,
        1.016,
        0.825,
        -178.86
      ],
      "distance": 10.62,
      "occluded": false
    },
    {
      "class": "vehicle",
      "actor_id": 230,
      "bbox_2d": [
        358,
        306,
        376,
        320
      ],
      "bbox_3d": [
        104.065,
        240.906,
        0.259,
        1.994,
        0.925,
        0.809,
        0.04
      ],
      "distance": 50.02,
      "occluded": false
    },
    {
      "class": "vehicle",
      "actor_id": 228,
      "bbox_2d": [
        738,
        307,
        788,
        320
      ],
      "bbox_3d": [
        102.296,
        191.6,
        0.216,
        2.446,
        0.918,
        0.745,
        0.01
      ],
      "distance": 68.71,
      "occluded": false
    }
  ]
}