{
  "frame_id": 500,
  "weather": "clear",
  "num_points": 18981,
  "num_radar": 195,
  "objects": [
    {
      "class": "vehicle",
      "actor_id": 238,
      "bbox_2d": [
        322,
        306,
        356,
        320
      ],
      "bbox_3d": [
        -6.414,
        113.033,
        0.211,
        1.853,
        0.894,
        0.775,
        116.33
      ],
      "distance": 51.6,
      "occluded": false
    },
    {
      "class": "vehicle",
      "actor_id": 236,
      "bbox_2d": [
        11,
        306,
        53,
        319
      ],
      "bbox_3d": [
        -7.438,
        152.095,
        0.201,
        1.817,
        0.923,
        0.751,
        90.13
      ],
      "distance": 69.93,
      "occluded": false
    },
    {
      "class": "vehicle",
      "actor_id": 234,
      "bbox_2d": [
        375,
        313,
        423,
        357
      ],
      "bbox_3d": [
        23.647,
        105.481,
        0.213,
        2.428,
        1.016,
        0.825,
        179.78
      ],
      "distance": 20.97,
      "occluded": false
    },
    {
      "class": "vehicle",
      "actor_id": 229,
      "bbox_2d": [
        386,
        307,
        412,
        328
      ],
      "bbox_3d": [
        6.511,
        105.629,
        0.363,
        2.513,
        1.076,
        0.825,
        178.5
      ],
      "distance": 38.11,
      "occluded": false
    },
    {
      "class": "vehicle",
      "actor_id": 222,
      "bbox_2d": [
        85,
        306,
        137,
        319
      ],
      "bbox_3d": [
        -7.419,
        142.041,
        0.361,
        2.513,
        1.076,
        0.825,
        90.03
      ],
      "distance": 63.64,
      "occluded": false
    },
    {
      "class": "vehicle",
      "actor_id": 221,
      "bbox_2d": [
        158,
        305,
        204,
        319
      ],
      "bbox_3d": [
        -7.417,
        133.098,
        0.287,
        2.306,
        1.121,
        0.834,
        89.9
      ],
      "distance": 58.95,
      "occluded": false
    },
    {
      "class": "vehicle",
      "actor_id": 215,
      "bbox_2d": [
        0,
        302,
        24,
        319
      ],
      "bbox_3d": [
        -7.448,
        157.445,
        0.217,
        3.137,
        1.195,
        1.049,
        90.11
      ],
      "distance": 73.61,
      "occluded": false
    }
  ]
}