{
  "frame_id": 3648,
  "weather": "clear",
  "num_points": 18800,
  "num_radar": 199,
  "objects": [
    {
      "class": "vehicle",
      "actor_id": 250,
      "bbox_2d": [
        714,
        311,
        785,
        327
      ],
      "bbox_3d": [
        45.844,
        205.414,
        0.215,
        2.359,
        0.947,
        0.65,
        -89.9
      ],
      "distance": 48.96,
      "occluded": false
    },
    {
      "class": "vehicle",
      "actor_id": 248,
      "bbox_2d": [
        0,
        310,
        26,
        324
      ],
      "bbox_3d": [
        41.858,
        277.364,
        0.214,
        2.359,
        0.947,
        0.65,
        89.98
      ],
      "distance": 57.95,
      "occluded": false
    },
    {
      "class": "vehicle",
      "actor_id": 244,
      "bbox_2d": [
        553,
        308,
        611,
        324
      ],
      "bbox_3d": [
        41.866,
        218.661,
        0.254,
        2.451,
        1.064,
        0.755,
        90.63
      ],
      "distance": 45.3,
      "occluded": false
    },
    {
      "class": "vehicle",
      "actor_id": 232,
      "bbox_2d": [
        367,
        322,
        432,
        384
      ],
      "bbox_3d": [
        68.11,
        236.883,
        0.213,
        2.446,
        0.918,
        0.745,
        -179.93
      ],
      "distance": 15.23,
      "occluded": false
    },
    {
      "class": "vehicle",
      "actor_id": 225,
      "bbox_2d": [
        99,
        309,
        164,
        327
      ],
      "bbox_3d": [
        45.856,
        260.822,
        0.257,
        2.257,
        1.003,
        0.762,
        -90.05
      ],
      "distance": 44.47,
      "occluded": false
    },
    {
      "class": "vehicle",
      "actor_id": 216,
      "bbox_2d": [
        382,
        316,
        417,
        344
      ],
      "bbox_3d": [
        57.845,
        236.882,
        0.214,
        2.359,
        0.947,
        0.65,
        -179.92
      ],
      "distance": 25.49,
      "occluded": false
    },
    {
      "class": "vehicle",
      "actor_id": 214,
      "bbox_2d": [
        607,
        302,
        685,
        324
      ],
      "bbox_3d": [
        41.928,
        212.351,
        0.217,
        3.137,
        1.195,
        1.049,
        90.9
      ],
      "distance": 48.14,
      "occluded": false
    }
  ]
}