{
  "frame_id": 17892,
  "weather": "rain",
  "num_points": 14822,
  "num_radar": 189,
  "objects": [
    {
      "class": "vehicle",
      "actor_id": 419,
      "bbox_2d": [
        0,
        305,
        27,
        318
      ],
      "bbox_3d": [
        -7.458,
        169.34,
        0.22,
        2.619,
        0.965,
        0.819,
        90.01
      ],
      "distance": 76.7,
      "occluded": false
    },
    {
      "class": "vehicle",
      "actor_id": 424,
      "bbox_2d": [
        379,
        305,
        417,
        342
      ],
      "bbox_3d": [
        45.662,
        197.723,
        0.223,
        2.24,
        1.035,
        1.019,
        -93.81
      ],
      "distance": 26.76,
      "occluded": false
    },
    {
      "class": "vehicle",
      "actor_id": 434,
      "bbox_2d": [
        642,
        309,
        717,
        327
      ],
      "bbox_3d": [
        70.674,
        187.585,
        0.239,
        2.683,
        0.9,
        0.787,
        -179.98
      ],
      "distance": 44.47,
      "occluded": false
    },
    {
      "class": "vehicle",
      "actor_id": 432,
      "bbox_2d": [
        257,
        318,
        338,
        369
      ],
      "bbox_3d": [
        41.907,
        206.508,
        0.19,
        2.487,
        1.019,
        0.771,
        90.42
      ],
      "distance": 18.4,
      "occluded": false
    },
    {
      "class": "vehicle",
      "actor_id": 401,
      "bbox_2d": [
        0,
        350,
        233,
        599
      ],
      "bbox_3d": [
        41.853,
        218.396,
        0.254,
        2.451,
        1.064,
        0.755,
        90.23
      ],
      "distance": 7.28,
      "occluded": false
    },
    {
      "class": "vehicle",
      "actor_id": 405,
      "bbox_2d": [
        322,
        341,
        477,
        488
      ],
      "bbox_3d": [
        45.852,
        215.978,
        0.262,
        1.903,
        0.985,
        0.738,
        -90.01
      ],
      "distance": 8.5,
      "occluded": false
    },
    {
      "class": "vehicle",
      "actor_id": 413,
      "bbox_2d": [
        374,
        320,
        424,
        367
      ],
      "bbox_3d": [
        45.838,
        206.306,
        0.219,
        2.337,
        0.906,
        0.721,
        -89.84
      ],
      "distance": 18.17,
      "occluded": false
    },
    {
      "class": "vehicle",
      "actor_id": 417,
      "bbox_2d": [
        590,
        308,
        647,
        328
      ],
      "bbox_3d": [
        65.16,
        187.583,
        0.259,
        1.994,
        0.925,
        0.809,
        179.97
      ],
      "distance": 41.64,
      "occluded": false
    },
    {
      "class": "vehicle",
      "actor_id": 421,
      "bbox_2d": [
        146,
        325,
        305,
        424
      ],
      "bbox_3d": [
        41.838,
        212.367,
        0.239,
        2.683,
        0.9,
        0.787,
        89.82
      ],
      "distance": 12.76,
      "occluded": false
    }
  ]
}