{
  "frame_id": 18330,
  "weather": "rain",
  "num_points": 14520,
  "num_radar": 192,
  "objects": [
    {
      "class": "vehicle",
      "actor_id": 422,
      "bbox_2d": [
        340,
        322,
        455,
        432
      ],
      "bbox_3d": [
        132.127,
        219.43,
        0.223,
        2.276,
        1.049,
        0.884,
        90.0
      ],
      "distance": 11.08,
      "occluded": false
    },
    {
      "class": "vehicle",
      "actor_id": 438,
      "bbox_2d": [
        0,
        288,
        141,
        509
      ],
      "bbox_3d": [
        136.14,
        211.602,
        0.198,
        2.958,
        0.994,
        1.28,
        -90.0
      ],
      "distance": 5.1,
      "occluded": false
    }
  ]
}