{
  "frame_id": 18334,
  "weather": "rain",
  "num_points": 14639,
  "num_radar": 184,
  "objects": [
    {
      "class": "vehicle",
      "actor_id": 422,
      "bbox_2d": [
        336,
        322,
        460,
        441
      ],
      "bbox_3d": [
        132.127,
        219.43,
        0.223,
        2.276,
        1.049,
        0.884,
        90.0
      ],
      "distance": 10.56,
      "occluded": false
    },
    {
      "class": "vehicle",
      "actor_id": 438,
      "bbox_2d": [
        0,
        285,
        110,
        533
      ],
      "bbox_3d": [
        136.14,
        211.602,
        0.198,
        2.958,
        0.994,
        1.28,
        -90.0
      ],
      "distance": 4.79,
      "occluded": false
    }
  ]
}