{
  "frame_id": 18256,
  "weather": "rain",
  "num_points": 14389,
  "num_radar": 107,
  "objects": [
    {
      "class": "vehicle",
      "actor_id": 402,
      "bbox_2d": [
        335,
        307,
        352,
        322
      ],
      "bbox_3d": [
        172.405,
        191.631,
        0.201,
        1.817,
        0.923,
        0.751,
        0.05
      ],
      "distance": 47.09,
      "occluded": false
    },
    {
      "class": "vehicle",
      "actor_id": 412,
      "bbox_2d": [
        328,
        303,
        355,
        329
      ],
      "bbox_3d": [
        162.141,
        191.603,
        0.223,
        2.783,
        1.075,
        1.023,
        0.18
      ],
      "distance": 36.82,
      "occluded": false
    },
    {
      "class": "vehicle",
      "actor_id": 411,
      "bbox_2d": [
        82,
        306,
        128,
        316
      ],
      "bbox_3d": [
        193.688,
        155.047,
        0.213,
        2.679,
        1.017,
        0.705,
        -89.94
      ],
      "distance": 77.67,
      "occluded": false
    },
    {
      "class": "vehicle",
      "actor_id": 420,
      "bbox_2d": [
        435,
        303,
        460,
        314
      ],
      "bbox_3d": [
        193.69,
        208.925,
        0.231,
        1.933,
        0.953,
        0.939,
        -89.99
      ],
      "distance": 70.45,
      "occluded": false
    },
    {
      "class": "vehicle",
      "actor_id": 439,
      "bbox_2d": [
        147,
        318,
        262,
        388
      ],
      "bbox_3d": [
        141.265,
        187.617,
        0.22,
        2.619,
        0.965,
        0.819,
        -179.97
      ],
      "distance": 16.51,
      "occluded": false
    },
    {
      "class": "vehicle",
      "actor_id": 427,
      "bbox_2d": [
        184,
        306,
        218,
        316
      ],
      "bbox_3d": [
        189.682,
        170.425,
        0.215,
        2.096,
        0.908,
        0.737,
        89.91
      ],
      "distance": 67.85,
      "occluded": false
    },
    {
      "class": "vehicle",
      "actor_id": 422,
      "bbox_2d": [
        681,
        332,
        799,
        490
      ],
      "bbox_3d": [
        132.124,
        200.26,
        0.223,
        2.276,
        1.049,
        0.884,
        91.36
      ],
      "distance": 10.77,
      "occluded": false
    },
    {
      "class": "vehicle",
      "actor_id": 416,
      "bbox_2d": [
        107,
        299,
        162,
        317
      ],
      "bbox_3d": [
        189.683,
        161.524,
        0.215,
        3.183,
        1.176,
        1.216,
        90.04
      ],
      "distance": 71.18,
      "occluded": false
    },
    {
      "class": "vehicle",
      "actor_id": 430,
      "bbox_2d": [
        459,
        303,
        490,
        315
      ],
      "bbox_3d": [
        189.709,
        212.455,
        0.223,
        2.276,
        1.049,
        0.884,
        90.05
      ],
      "distance": 67.59,
      "occluded": false
    },
    {
      "class": "vehicle",
      "actor_id": 410,
      "bbox_2d": [
        713,
        306,
        753,
        319
      ],
      "bbox_3d": [
        172.251,
        240.949,
        0.212,
        1.853,
        0.894,
        0.775,
        -0.02
      ],
      "distance": 67.88,
      "occluded": false
    },
    {
      "class": "vehicle",
      "actor_id": 404,
      "bbox_2d": [
        257,
        313,
        302,
        339
      ],
      "bbox_3d": [
        154.817,
        187.626,
        0.212,
        2.679,
        1.017,
        0.705,
        -179.92
      ],
      "distance": 29.81,
      "occluded": false
    },
    {
      "class": "vehicle",
      "actor_id": 409,
      "bbox_2d": [
        333,
        308,
        353,
        324
      ],
      "bbox_3d": [
        168.202,
        191.628,
        0.262,
        1.903,
        0.985,
        0.738,
        0.27
      ],
      "distance": 42.88,
      "occluded": false
    },
    {
      "class": "vehicle",
      "actor_id": 415,
      "bbox_2d": [
        744,
        307,
        799,
        321
      ],
      "bbox_3d": [
        167.569,
        240.954,
        0.219,
        2.337,
        0.906,
        0.721,
        -0.15
      ],
      "distance": 64.73,
      "occluded": false
    },
    {
      "class": "vehicle",
      "actor_id": 440,
      "bbox_2d": [
        305,
        305,
        324,
        318
      ],
      "bbox_3d": [
        182.292,
        187.634,
        0.22,
        2.619,
        0.965,
        0.819,
        -176.84
      ],
      "distance": 57.13,
      "occluded": false
    }
  ]
}