{
  "frame_id": 5248,
  "weather": "fog_light",
  "num_points": 15604,
  "num_radar": 107,
  "objects": [
    {
      "class": "vehicle",
      "actor_id": 271,
      "bbox_2d": [
        382,
        310,
        403,
        328
      ],
      "bbox_3d": [
        49.04,
        191.574,
        0.219,
        2.337,
        0.906,
        0.721,
        0.02
      ],
      "distance": 37.71,
      "occluded": false
    },
    {
      "class": "vehicle",
      "actor_id": 267,
      "bbox_2d": [
        579,
        310,
        641,
        329
      ],
      "bbox_3d": [
        45.843,
        209.642,
        0.215,
        2.096,
        0.908,
        0.737,
        -89.85
      ],
      "distance": 39.02,
      "occluded": false
    },
    {
      "class": "vehicle",
      "actor_id": 270,
      "bbox_2d": [
        724,
        299,
        783,
        318
      ],
      "bbox_3d": [
        66.886,
        240.821,
        0.215,
        3.183,
        1.176,
        1.216,
        0.83
      ],
      "distance": 74.33,
      "occluded": false
    },
    {
      "class": "vehicle",
      "actor_id": 280,
      "bbox_2d": [
        0,
        357,
        181,
        599
      ],
      "bbox_3d": [
        16.129,
        187.56,
        0.239,
        2.683,
        0.9,
        0.787,
        -179.98
      ],
      "distance": 6.17,
      "occluded": false
    },
    {
      "class": "vehicle",
      "actor_id": 292,
      "bbox_2d": [
        703,
        310,
        796,
        333
      ],
      "bbox_3d": [
        41.865,
        217.656,
        0.239,
        2.683,
        0.9,
        0.787,
        90.19
      ],
      "distance": 40.24,
      "occluded": false
    },
    {
      "class": "vehicle",
      "actor_id": 297,
      "bbox_2d": [
        386,
        304,
        398,
        314
      ],
      "bbox_3d": [
        83.317,
        191.59,
        0.192,
        2.487,
        1.019,
        0.771,
        0.05
      ],
      "distance": 71.99,
      "occluded": false
    },
    {
      "class": "vehicle",
      "actor_id": 306,
      "bbox_2d": [
        341,
        338,
        452,
        440
      ],
      "bbox_3d": [
        22.033,
        191.548,
        0.214,
        2.359,
        0.947,
        0.65,
        -0.41
      ],
      "distance": 10.7,
      "occluded": false
    }
  ]
}