{
  "frame_id": 9678,
  "weather": "fog_light",
  "num_points": 16086,
  "num_radar": 200,
  "objects": [
    {
      "class": "vehicle",
      "actor_id": 271,
      "bbox_2d": [
        379,
        312,
        406,
        335
      ],
      "bbox_3d": [
        193.694,
        259.824,
        0.219,
        2.337,
        0.906,
        0.721,
        -89.9
      ],
      "distance": 30.83,
      "occluded": false
    },
    {
      "class": "vehicle",
      "actor_id": 279,
      "bbox_2d": [
        366,
        314,
        419,
        359
      ],
      "bbox_3d": [
        193.689,
        270.493,
        0.361,
        2.513,
        1.076,
        0.825,
        -90.0
      ],
      "distance": 20.16,
      "occluded": false
    },
    {
      "class": "vehicle",
      "actor_id": 273,
      "bbox_2d": [
        386,
        304,
        399,
        314
      ],
      "bbox_3d": [
        193.73,
        219.728,
        0.19,
        2.487,
        1.019,
        0.771,
        -90.28
      ],
      "distance": 70.93,
      "occluded": false
    },
    {
      "class": "vehicle",
      "actor_id": 270,
      "bbox_2d": [
        257,
        297,
        538,
        590
      ],
      "bbox_3d": [
        193.716,
        282.338,
        0.215,
        3.183,
        1.176,
        1.216,
        -90.3
      ],
      "distance": 8.32,
      "occluded": false
    },
    {
      "class": "vehicle",
      "actor_id": 277,
      "bbox_2d": [
        335,
        308,
        363,
        328
      ],
      "bbox_3d": [
        189.899,
        252.672,
        0.24,
        2.683,
        0.9,
        0.787,
        91.5
      ],
      "distance": 38.17,
      "occluded": false
    },
    {
      "class": "vehicle",
      "actor_id": 285,
      "bbox_2d": [
        373,
        305,
        411,
        343
      ],
      "bbox_3d": [
        193.685,
        264.843,
        0.223,
        2.24,
        1.035,
        1.019,
        -89.85
      ],
      "distance": 25.81,
      "occluded": false
    },
    {
      "class": "vehicle",
      "actor_id": 292,
      "bbox_2d": [
        266,
        306,
        314,
        320
      ],
      "bbox_3d": [
        181.28,
        240.788,
        0.238,
        2.683,
        0.9,
        0.787,
        -2.89
      ],
      "distance": 51.38,
      "occluded": false
    },
    {
      "class": "vehicle",
      "actor_id": 305,
      "bbox_2d": [
        356,
        314,
        430,
        392
      ],
      "bbox_3d": [
        193.69,
        276.38,
        0.221,
        2.302,
        0.966,
        0.927,
        -90.58
      ],
      "distance": 14.27,
      "occluded": false
    },
    {
      "class": "vehicle",
      "actor_id": 306,
      "bbox_2d": [
        87,
        309,
        138,
        320
      ],
      "bbox_3d": [
        160.466,
        240.947,
        0.215,
        2.359,
        0.947,
        0.65,
        -0.05
      ],
      "distance": 59.77,
      "occluded": false
    }
  ]
}